src/__init__.py
src/mhaptk2.py
pymHapTk2-1.0.0.dist-info/LICENSE.txt
pymHapTk2-1.0.0.dist-info/METADATA
pymHapTk2-1.0.0.dist-info/WHEEL
pymHapTk2-1.0.0.dist-info/entry_points.txt
pymHapTk2-1.0.0.dist-info/top_level.txt
pymHapTk2-1.0.0.dist-info/RECORD
