Metadata-Version: 2.1
Name: pymHapTk2
Version: 1.0.0
Summary: mHapTk is a tool kit for analysis of DNA methylation haplotypes. It has 5 sub-commands: tanghulu, stat, genomeWide, R2 and MHBDiscovery
Author: ckw
Author-email: 1353595807@qq.com
License-File: LICENSE.txt
